TOPSIS/__init__.py
TOPSIS/__main__.py
TOPSIS_Aadarsh-1.1.0.dist-info/Licence.txt
TOPSIS_Aadarsh-1.1.0.dist-info/METADATA
TOPSIS_Aadarsh-1.1.0.dist-info/WHEEL
TOPSIS_Aadarsh-1.1.0.dist-info/entry_points.txt
TOPSIS_Aadarsh-1.1.0.dist-info/top_level.txt
TOPSIS_Aadarsh-1.1.0.dist-info/RECORD
