Metadata-Version: 2.1
Name: TOPSIS-Aadarsh
Version: 1.1.0
Summary: TOPSIS
Home-page: https://github.com/infinity1013/Topsis
Author: Aadarsh Gupta
Author-email: aadarshgupta875@gmail.com
License: MIT
Platform: UNKNOWN
Classifier: License :: OSI Approved :: MIT License
Classifier: Programming Language :: Python :: 3.6
Classifier: Programming Language :: Python :: 3.7
Classifier: Programming Language :: Python :: 3.8
